bt_visualizer/__init__.py
bt_visualizer/bt-visualizer.css
bt_visualizer/bt-visualizer.js
bt_visualizer/visualizer.py
bt_visualizer-0.2.3.dist-info/METADATA
bt_visualizer-0.2.3.dist-info/WHEEL
bt_visualizer-0.2.3.dist-info/top_level.txt
bt_visualizer-0.2.3.dist-info/RECORD
