Metadata-Version: 2.4
Name: bt-visualizer
Version: 0.2.3
Summary: Backtest visualization widget for JupyterLab
Author: Your Name
Author-email: Ali Gheshlaghi <aliigheshlaghi97@email.com>
License: MIT
Project-URL: Homepage, https://finance-insight-lab.github.io/bt-visualizer/
Project-URL: Repository, https://github.com/Finance-Insight-Lab/bt-visualizer
Requires-Dist: anywidget<1.0,>=0.9
Requires-Dist: traitlets<6.0,>=5.9
Requires-Dist: IPython<9.0,>=8.12
